formic_opcua/__init__.py
formic_opcua/client/__init__.py
formic_opcua/client/async_opcua_client.py
formic_opcua/client/opcua_client.py
formic_opcua/client/subscription_handler.py
formic_opcua/core/__init__.py
formic_opcua/core/connection_delays.py
formic_opcua/core/exceptions.py
formic_opcua/core/parse.py
formic_opcua/core/type_conversions.py
formic_opcua/scripts/__init__.py
formic_opcua/scripts/formic_opcua_client.py
formic_opcua/scripts/formic_opcua_server.py
formic_opcua/server/__init__.py
formic_opcua/server/opcua_server.py
formic_opcua-1.8.0.dist-info/METADATA
formic_opcua-1.8.0.dist-info/WHEEL
formic_opcua-1.8.0.dist-info/entry_points.txt
formic_opcua-1.8.0.dist-info/RECORD
